parameter_sherpa-1.0.2.dist-info/DESCRIPTION.rst
parameter_sherpa-1.0.2.dist-info/METADATA
parameter_sherpa-1.0.2.dist-info/RECORD
parameter_sherpa-1.0.2.dist-info/WHEEL
parameter_sherpa-1.0.2.dist-info/metadata.json
parameter_sherpa-1.0.2.dist-info/top_level.txt
sherpa/__init__.py
sherpa/algorithms.py
sherpa/core.py
sherpa/database.py
sherpa/schedulers.py
sherpa/successive_halving.py
sherpa/algorithms/__init__.py
sherpa/algorithms/bayesian_optimization.py
sherpa/algorithms/core.py
sherpa/algorithms/successive_halving.py
sherpa/app/PARALLELCOORDINATESLICENSE
sherpa/app/__init__.py
sherpa/app/__init__.pyc
sherpa/app/app.py
sherpa/app/app.pyc
sherpa/app/__pycache__/__init__.cpython-36.pyc
sherpa/app/__pycache__/app.cpython-36.pyc
sherpa/app/static/d3/d3.js
sherpa/app/static/d3/d3.v3.js
sherpa/app/static/dialog-polyfill-master/.gitignore
sherpa/app/static/dialog-polyfill-master/LICENSE
sherpa/app/static/dialog-polyfill-master/README.md
sherpa/app/static/dialog-polyfill-master/bower.json
sherpa/app/static/dialog-polyfill-master/dialog-polyfill.css
sherpa/app/static/dialog-polyfill-master/dialog-polyfill.js
sherpa/app/static/dialog-polyfill-master/package.json
sherpa/app/static/dialog-polyfill-master/suite.js
sherpa/app/static/dialog-polyfill-master/test.html
sherpa/app/static/dialog-polyfill-master/tests/actionbar.html
sherpa/app/static/dialog-polyfill-master/tests/backdrop.html
sherpa/app/static/dialog-polyfill-master/tests/dialog-centering.html
sherpa/app/static/dialog-polyfill-master/tests/dialog-recentering.html
sherpa/app/static/dialog-polyfill-master/tests/fancy-modal-dialog.html
sherpa/app/static/dialog-polyfill-master/tests/form.html
sherpa/app/static/dialog-polyfill-master/tests/modal-dialog-stacking.html
sherpa/app/static/dialog-polyfill-master/tests/modal-dialog.html
sherpa/app/static/dialog-polyfill-master/tests/respect-positioned-dialog.html
sherpa/app/static/dialog-polyfill-master/tests/stacking.html
sherpa/app/static/dialog-polyfill-master/tests/resources/close_dialog.png
sherpa/app/static/dialog-polyfill-master/tests/resources/close_dialog_hover.png
sherpa/app/static/lib/d3.js
sherpa/app/static/lib/d3.min.js
sherpa/app/static/lib/d3.parcoords.css
