Metadata-Version: 2.0
Name: parameter-sherpa
Version: 1.0.2
Summary: Hyperparameter Optimization for Machine Learning Models.
Home-page: https://github.com/sherpa-ai/sherpa
Author: Lars Hertel, Peter Sadowski, and Julian Collado
Author-email: lhertel@uci.edu
License: GPLv3
Keywords: hyperparameter optimization machine-learning
Platform: UNKNOWN
Classifier: Development Status :: 3 - Alpha
Classifier: License :: OSI Approved :: GNU General Public License v3 (GPLv3)
Classifier: Programming Language :: Python
Classifier: Programming Language :: Python :: 2.6
Classifier: Programming Language :: Python :: 2.7
Classifier: Programming Language :: Python :: 3
Classifier: Programming Language :: Python :: 3.3
Classifier: Programming Language :: Python :: 3.4
Classifier: Programming Language :: Python :: 3.5
Classifier: Programming Language :: Python :: 3.6
Classifier: Programming Language :: Python :: Implementation :: CPython
Classifier: Programming Language :: Python :: Implementation :: PyPy
Requires-Dist: drmaa (>=0.7.7)
Requires-Dist: flask (>=0.12.2)
Requires-Dist: numpy (>=1.8.2)
Requires-Dist: pandas (>=0.20.3)
Requires-Dist: pymongo (>=3.5.1)
Requires-Dist: pymongo (>=3.5.1)
Requires-Dist: scikit-learn (>=0.19.1)
Requires-Dist: scipy (>=1.0.0)
